marknote/__init__.py
marknote/apps.py
marknote/models.py
marknote/serializers.py
marknote/urls.py
marknote/views.py
marknote/migrations/0001_initial.py
marknote/migrations/__init__.py
marknote/tests/__init__.py
marknote/tests/test_folder.py
marknote/tests/test_note.py
marknote-1.0.2.dist-info/METADATA
marknote-1.0.2.dist-info/RECORD
marknote-1.0.2.dist-info/WHEEL
marknote-1.0.2.dist-info/top_level.txt
