Metadata-Version: 2.1
Name: marknote
Version: 1.0.2
Summary: A simple note taking API for Django that supports creating notes and a folder structure. Built for the purpose of learning how to use the Django REST Framework to build a CRUD API.
Home-page: https://github.com/sheldonkwoodward/marknote
Author: Sheldon Woodward
Author-email: contact@sheldonw.com
License: MIT
Keywords: django rest api notes
Platform: UNKNOWN
Classifier: Framework :: Django :: 2.0
Classifier: Framework :: Django :: 2.1
Classifier: Intended Audience :: Developers
Classifier: License :: Public Domain
Classifier: Natural Language :: English
Classifier: Operating System :: OS Independent
Classifier: Programming Language :: Python
Classifier: Programming Language :: Python :: 3
Classifier: Programming Language :: Python :: 3.5
Classifier: Programming Language :: Python :: 3.6
Classifier: Programming Language :: Python :: 3.7
Classifier: Topic :: Internet :: WWW/HTTP
Requires-Python: >=3.5
Requires-Dist: django
Requires-Dist: djangorestframework
